{
  "users": [
    {
      "id": "1",
      "email": "dbao.le332@gmail.com",
      "userName": "dbao5",
      "fullName": "Bảo Duy Lê",
      "department": "Marketing6",
      "position": "Sale6"
    },
    {
      "id": "2",
      "email": "2051120207@ut.edu.vn",
      "userName": "ryuu",
      "fullName": "duybao",
      "department": "it",
      "position": "it"
    },
    {
      "id": "",
      "email": "",
      "userName": "",
      "fullName": "",
      "department": "",
      "position": ""
    },
    {
      "id": "",
      "email": "",
      "userName": "",
      "fullName": "",
      "department": "",
      "position": ""
    }
  ]
}